<?xml version="1.0" encoding="utf-8" ?><dwsync><file name="return_action.php" server="u293625.ftp.masterhost.ru//liveolive.ru/www/" local="3386846648" remote="11982115232" /><file name="return_reason.php" server="u293625.ftp.masterhost.ru//liveolive.ru/www/" local="3386846648" remote="11982115232" /><file name="return_status.php" server="u293625.ftp.masterhost.ru//liveolive.ru/www/" local="3386846648" remote="11982115232" /><file name="country.php" server="u293625.ftp.masterhost.ru//liveolive.ru/www/" local="3358759928" remote="11982115232" /><file name="currency.php" server="u293625.ftp.masterhost.ru//liveolive.ru/www/" local="3358759928" remote="11982115232" /><file name="geo_zone.php" server="u293625.ftp.masterhost.ru//liveolive.ru/www/" local="3358759928" remote="11982115232" /><file name="language.php" server="u293625.ftp.masterhost.ru//liveolive.ru/www/" local="3358759928" remote="11982115232" /><file name="length_class.php" server="u293625.ftp.masterhost.ru//liveolive.ru/www/" local="3392799136" remote="16277701008" /><file name="order_status.php" server="u293625.ftp.masterhost.ru//liveolive.ru/www/" local="3358759928" remote="11982115232" /><file name="stock_status.php" server="u293625.ftp.masterhost.ru//liveolive.ru/www/" local="3358759928" remote="11982115232" /><file name="tax_class.php" server="u293625.ftp.masterhost.ru//liveolive.ru/www/" local="3358759928" remote="11982115232" /><file name="weight_class.php" server="u293625.ftp.masterhost.ru//liveolive.ru/www/" local="3392800696" remote="16277702568" /><file name="zone.php" server="u293625.ftp.masterhost.ru//liveolive.ru/www/" local="3358759928" remote="11982115232" /></dwsync>